spinta/__init__.py
spinta/__main__.py
spinta/accesslog/__init__.py
spinta/accesslog/file.py
spinta/accesslog/python.py
spinta/api/__init__.py
spinta/api/inspect.py
spinta/api/schema.py
spinta/asgi.py
spinta/auth.py
spinta/backends/__init__.py
spinta/backends/components.py
spinta/backends/constants.py
spinta/backends/fs/__init__.py
spinta/backends/fs/commands/__init__.py
spinta/backends/fs/commands/bootstrap.py
spinta/backends/fs/commands/changes.py
spinta/backends/fs/commands/decode.py
spinta/backends/fs/commands/encode.py
spinta/backends/fs/commands/init.py
spinta/backends/fs/commands/load.py
spinta/backends/fs/commands/migrate.py
spinta/backends/fs/commands/read.py
spinta/backends/fs/commands/validate.py
spinta/backends/fs/commands/wait.py
spinta/backends/fs/commands/wipe.py
spinta/backends/fs/commands/write.py
spinta/backends/fs/components.py
spinta/backends/helpers.py
spinta/backends/memory/__init__.py
spinta/backends/memory/commands/__init__.py
spinta/backends/memory/commands/auth.py
spinta/backends/memory/commands/bootstrap.py
spinta/backends/memory/commands/changes.py
spinta/backends/memory/commands/check.py
spinta/backends/memory/commands/encode.py
spinta/backends/memory/commands/init.py
spinta/backends/memory/commands/load.py
spinta/backends/memory/commands/manifest.py
spinta/backends/memory/commands/read.py
spinta/backends/memory/commands/wait.py
spinta/backends/memory/commands/wipe.py
spinta/backends/memory/commands/write.py
spinta/backends/memory/components.py
spinta/backends/mongo/__init__.py
spinta/backends/mongo/commands/__init__.py
spinta/backends/mongo/commands/bootstrap.py
spinta/backends/mongo/commands/changes.py
spinta/backends/mongo/commands/encode.py
spinta/backends/mongo/commands/freeze.py
spinta/backends/mongo/commands/init.py
spinta/backends/mongo/commands/load.py
spinta/backends/mongo/commands/migrate.py
spinta/backends/mongo/commands/read.py
spinta/backends/mongo/commands/validate.py
spinta/backends/mongo/commands/wait.py
spinta-0.1.85.dist-info/LICENSE
spinta-0.1.85.dist-info/METADATA
spinta-0.1.85.dist-info/WHEEL
spinta-0.1.85.dist-info/entry_points.txt
spinta-0.1.85.dist-info/RECORD
