Metadata-Version: 2.1
Name: spinta
Version: 0.1.85
Summary: A platform for describing, extracting, transforming, loading and serving open data.
Home-page: https://gitlab.com/atviriduomenys/spinta
License: MIT
Author: Mantas Zimnickas
Author-email: sirexas@gmail.com
Requires-Python: >=3.8,<4.0
Classifier: Development Status :: 2 - Pre-Alpha
Classifier: Environment :: Console
Classifier: Environment :: Web Environment
Classifier: Intended Audience :: Developers
Classifier: Intended Audience :: System Administrators
Classifier: License :: OSI Approved :: MIT License
Classifier: Operating System :: POSIX
Classifier: Operating System :: POSIX :: Linux
Classifier: Programming Language :: Python :: 3
Classifier: Programming Language :: Python :: 3.8
Classifier: Programming Language :: Python :: 3.9
Classifier: Programming Language :: Python :: 3.10
Classifier: Programming Language :: Python :: 3.11
Classifier: Topic :: Database
Classifier: Topic :: Database :: Database Engines/Servers
Classifier: Topic :: Database :: Front-Ends
Requires-Dist: GeoAlchemy2
Requires-Dist: Shapely
Requires-Dist: XlsxWriter
Requires-Dist: aiofiles
Requires-Dist: aiohttp
Requires-Dist: alembic (>=1.11.0,<1.12.0)
Requires-Dist: asyncpg
Requires-Dist: authlib (>=0.11,<0.12)
Requires-Dist: cachetools
Requires-Dist: click
Requires-Dist: dask[dataframe]
Requires-Dist: fsspec
Requires-Dist: gunicorn
Requires-Dist: jinja2
Requires-Dist: jsonpatch
Requires-Dist: lark-parser
Requires-Dist: lxml
Requires-Dist: msgpack
Requires-Dist: multipledispatch
Requires-Dist: numpy
Requires-Dist: openpyxl
Requires-Dist: phonenumbers
Requires-Dist: pprintpp
Requires-Dist: psutil
Requires-Dist: psycopg2-binary
Requires-Dist: pymongo (<=4.8.0)
Requires-Dist: pyproj
Requires-Dist: python-multipart
Requires-Dist: pytz
Requires-Dist: rdflib
Requires-Dist: requests
Requires-Dist: ruamel.yaml
Requires-Dist: setuptools
Requires-Dist: setuptools-scm
Requires-Dist: sqlalchemy (>=1.4,<1.5)
Requires-Dist: sqlalchemy-utils
Requires-Dist: sqlean-py
Requires-Dist: sqlparse
Requires-Dist: starlette (>=0.40)
Requires-Dist: tabulate
Requires-Dist: toposort
Requires-Dist: tqdm
Requires-Dist: typer[all]
Requires-Dist: ujson
Requires-Dist: unidecode
Requires-Dist: uvicorn
Requires-Dist: xlrd
Requires-Dist: xmltodict
Project-URL: Bug Tracker, https://gitlab.com/atviriduomenys/spinta/-/issues
Project-URL: Documentation, https://spinta.readthedocs.io/
Project-URL: Repository, https://gitlab.com/atviriduomenys/spinta
